{
  "GTIN": "4573102664600",
  "ASIN": "B0CWBPZ884",
  "parsedPriceHistory": {
    "amazonPriceHistory": [
      {
        "date": "2024-10-01T14:28:00.000Z",
        "priceUSD": null
      }
    ],
    "marketplaceNewPriceHistory": [
      {
        "date": "2024-10-01T14:28:00.000Z",
        "priceUSD": 279.29
      },
      {
        "date": "2024-10-22T17:10:00.000Z",
        "priceUSD": 300
      },
      {
        "date": "2024-10-25T21:20:00.000Z",
        "priceUSD": null
      },
      {
        "date": "2024-10-30T21:34:00.000Z",
        "priceUSD": 198
      },
      {
        "date": "2024-11-11T21:10:00.000Z",
        "priceUSD": 224.99
      },
      {
        "date": "2024-11-12T15:48:00.000Z",
        "priceUSD": 249.99
      },
      {
        "date": "2024-11-17T12:18:00.000Z",
        "priceUSD": 188
      },
      {
        "date": "2024-11-18T06:40:00.000Z",
        "priceUSD": 195
      },
      {
        "date": "2024-11-20T23:14:00.000Z",
        "priceUSD": 189
      },
      {
        "date": "2024-11-30T00:52:00.000Z",
        "priceUSD": 198
      },
      {
        "date": "2024-12-04T20:26:00.000Z",
        "priceUSD": 282.25
      },
      {
        "date": "2024-12-05T13:02:00.000Z",
        "priceUSD": 273.27
      },
      {
        "date": "2024-12-06T14:32:00.000Z",
        "priceUSD": 274.52
      },
      {
        "date": "2024-12-07T18:34:00.000Z",
        "priceUSD": 275.59
      },
      {
        "date": "2024-12-09T04:30:00.000Z",
        "priceUSD": 275.44
      },
      {
        "date": "2024-12-09T06:36:00.000Z",
        "priceUSD": 227.44
      },
      {
        "date": "2024-12-09T11:38:00.000Z",
        "priceUSD": 227.23
      },
      {
        "date": "2024-12-09T15:46:00.000Z",
        "priceUSD": 227.17
      },
      {
        "date": "2024-12-23T03:12:00.000Z",
        "priceUSD": 223.33
      },
      {
        "date": "2024-12-23T06:18:00.000Z",
        "priceUSD": 223.25
      },
      {
        "date": "2024-12-24T15:40:00.000Z",
        "priceUSD": 194
      },
      {
        "date": "2024-12-28T19:22:00.000Z",
        "priceUSD": 209
      },
      {
        "date": "2025-01-15T18:22:00.000Z",
        "priceUSD": 213
      },
      {
        "date": "2025-01-15T21:30:00.000Z",
        "priceUSD": 153.2
      },
      {
        "date": "2025-01-15T23:20:00.000Z",
        "priceUSD": 170.8
      },
      {
        "date": "2025-01-24T19:22:00.000Z",
        "priceUSD": 181.15
      }
    ],
    "marketplaceUsedPriceHistory": [
      {
        "date": "2024-10-01T14:28:00.000Z",
        "priceUSD": null
      }
    ],
    "salesRankHistory": [
      {
        "date": "2024-10-01T17:34:00.000Z",
        "priceUSD": null
      },
      {
        "date": "2024-11-03T22:04:00.000Z",
        "priceUSD": 5888.54
      },
      {
        "date": "2024-11-04T07:24:00.000Z",
        "priceUSD": 9264.38
      },
      {
        "date": "2024-11-04T19:48:00.000Z",
        "priceUSD": 10340.14
      },
      {
        "date": "2024-11-05T11:28:00.000Z",
        "priceUSD": 104405.89
      },
      {
        "date": "2024-11-05T22:26:00.000Z",
        "priceUSD": 104138.01
      },
      {
        "date": "2024-11-06T11:36:00.000Z",
        "priceUSD": 104176.02
      },
      {
        "date": "2024-11-07T00:06:00.000Z",
        "priceUSD": 104267.51
      },
      {
        "date": "2024-11-07T14:34:00.000Z",
        "priceUSD": 4340.47
      },
      {
        "date": "2024-11-08T04:00:00.000Z",
        "priceUSD": 5740.59
      },
      {
        "date": "2024-11-08T17:26:00.000Z",
        "priceUSD": 9268.1
      },
      {
        "date": "2024-11-09T05:48:00.000Z",
        "priceUSD": 10941.81
      },
      {
        "date": "2024-11-09T21:32:00.000Z",
        "priceUSD": 11985.81
      },
      {
        "date": "2024-11-10T07:24:00.000Z",
        "priceUSD": 12765.73
      },
      {
        "date": "2024-11-10T22:26:00.000Z",
        "priceUSD": 14240.79
      },
      {
        "date": "2024-11-11T10:30:00.000Z",
        "priceUSD": 15828.91
      },
      {
        "date": "2024-11-11T21:10:00.000Z",
        "priceUSD": 16783.47
      },
      {
        "date": "2024-11-12T07:26:00.000Z",
        "priceUSD": 4852.52
      },
      {
        "date": "2024-11-13T01:06:00.000Z",
        "priceUSD": 7327.09
      },
      {
        "date": "2024-11-13T10:30:00.000Z",
        "priceUSD": 9736.65
      },
      {
        "date": "2024-11-13T19:54:00.000Z",
        "priceUSD": 10451.07
      },
      {
        "date": "2024-11-13T23:02:00.000Z",
        "priceUSD": 10633.66
      },
      {
        "date": "2024-11-14T02:10:00.000Z",
        "priceUSD": 11689.21
      },
      {
        "date": "2024-11-14T09:54:00.000Z",
        "priceUSD": 12500.19
      },
      {
        "date": "2024-11-14T18:00:00.000Z",
        "priceUSD": 13002.09
      },
      {
        "date": "2024-11-15T00:08:00.000Z",
        "priceUSD": 13720.09
      },
      {
        "date": "2024-11-15T05:20:00.000Z",
        "priceUSD": 13892.81
      },
      {
        "date": "2024-11-15T08:46:00.000Z",
        "priceUSD": 14423.84
      },
      {
        "date": "2024-11-15T11:30:00.000Z",
        "priceUSD": 14564.51
      },
      {
        "date": "2024-11-15T16:00:00.000Z",
        "priceUSD": 14683.1
      },
      {
        "date": "2024-11-15T19:50:00.000Z",
        "priceUSD": 15138.65
      },
      {
        "date": "2024-11-16T00:16:00.000Z",
        "priceUSD": 15736.76
      },
      {
        "date": "2024-11-16T08:20:00.000Z",
        "priceUSD": 16244.41
      },
      {
        "date": "2024-11-16T15:34:00.000Z",
        "priceUSD": 16889.35
      },
      {
        "date": "2024-11-16T20:56:00.000Z",
        "priceUSD": 17321.95
      },
      {
        "date": "2024-11-17T03:52:00.000Z",
        "priceUSD": 18200.73
      },
      {
        "date": "2024-11-17T07:00:00.000Z",
        "priceUSD": 18361.1
      },
      {
        "date": "2024-11-17T12:18:00.000Z",
        "priceUSD": 18765.67
      },
      {
        "date": "2024-11-17T18:16:00.000Z",
        "priceUSD": 19110.25
      },
      {
        "date": "2024-11-18T01:30:00.000Z",
        "priceUSD": 19918.12
      },
      {
        "date": "2024-11-18T06:40:00.000Z",
        "priceUSD": 5081.71
      },
      {
        "date": "2024-11-18T11:52:00.000Z",
        "priceUSD": 5972.72
      },
      {
        "date": "2024-11-18T15:58:00.000Z",
        "priceUSD": 6643.11
      },
      {
        "date": "2024-11-18T21:08:00.000Z",
        "priceUSD": 7473.83
      },
      {
        "date": "2024-11-19T03:50:00.000Z",
        "priceUSD": 8787.65
      },
      {
        "date": "2024-11-19T06:58:00.000Z",
        "priceUSD": 9458.06
      },
      {
        "date": "2024-11-19T10:52:00.000Z",
        "priceUSD": 9764.55
      },
      {
        "date": "2024-11-19T14:00:00.000Z",
        "priceUSD": 10236.74
      },
      {
        "date": "2024-11-19T17:08:00.000Z",
        "priceUSD": 10487.1
      },
      {
        "date": "2024-11-20T01:32:00.000Z",
        "priceUSD": 11602.74
      },
      {
        "date": "2024-11-20T08:46:00.000Z",
        "priceUSD": 12366.27
      },
      {
        "date": "2024-11-20T11:56:00.000Z",
        "priceUSD": 12526.88
      },
      {
        "date": "2024-11-20T17:02:00.000Z",
        "priceUSD": 12747.92
      },
      {
        "date": "2024-11-20T23:14:00.000Z",
        "priceUSD": 13503.99
      },
      {
        "date": "2024-11-21T04:38:00.000Z",
        "priceUSD": 13888.73
      },
      {
        "date": "2024-11-21T08:48:00.000Z",
        "priceUSD": 14453.53
      },
      {
        "date": "2024-11-21T13:56:00.000Z",
        "priceUSD": 14663.19
      },
      {
        "date": "2024-11-21T20:08:00.000Z",
        "priceUSD": 15396.28
      },
      {
        "date": "2024-11-22T02:16:00.000Z",
        "priceUSD": 5699.52
      },
      {
        "date": "2024-11-22T07:40:00.000Z",
        "priceUSD": 6765.75
      },
      {
        "date": "2024-11-22T10:48:00.000Z",
        "priceUSD": 7693.71
      },
      {
        "date": "2024-11-22T14:40:00.000Z",
        "priceUSD": 8021.08
      },
      {
        "date": "2024-11-22T21:54:00.000Z",
        "priceUSD": 9148.01
      },
      {
        "date": "2024-11-23T04:06:00.000Z",
        "priceUSD": 4850.49
      },
      {
        "date": "2024-11-23T09:16:00.000Z",
        "priceUSD": 6174.14
      },
      {
        "date": "2024-11-23T16:30:00.000Z",
        "priceUSD": 6821.67
      },
      {
        "date": "2024-11-23T23:42:00.000Z",
        "priceUSD": 7972.4
      },
      {
        "date": "2024-11-24T04:26:00.000Z",
        "priceUSD": 8832.92
      },
      {
        "date": "2024-11-24T07:32:00.000Z",
        "priceUSD": 9483.13
      },
      {
        "date": "2024-11-24T09:16:00.000Z",
        "priceUSD": 9693.09
      },
      {
        "date": "2024-11-24T12:24:00.000Z",
        "priceUSD": 9901.47
      },
      {
        "date": "2024-11-24T14:46:00.000Z",
        "priceUSD": 9961.25
      },
      {
        "date": "2024-11-24T16:56:00.000Z",
        "priceUSD": 10039.76
      },
      {
        "date": "2024-11-24T20:24:00.000Z",
        "priceUSD": 10585.64
      },
      {
        "date": "2024-11-25T00:30:00.000Z",
        "priceUSD": 11148.78
      },
      {
        "date": "2024-11-25T06:42:00.000Z",
        "priceUSD": 11806.42
      },
      {
        "date": "2024-11-25T12:08:00.000Z",
        "priceUSD": 12262.26
      },
      {
        "date": "2024-11-25T14:16:00.000Z",
        "priceUSD": 12306.58
      },
      {
        "date": "2024-11-25T17:22:00.000Z",
        "priceUSD": 12449.7
      },
      {
        "date": "2024-11-25T20:30:00.000Z",
        "priceUSD": 12604.75
      },
      {
        "date": "2024-11-25T23:38:00.000Z",
        "priceUSD": 13036.4
      },
      {
        "date": "2024-11-26T02:44:00.000Z",
        "priceUSD": 13417.88
      },
      {
        "date": "2024-11-26T05:28:00.000Z",
        "priceUSD": 13582.08
      },
      {
        "date": "2024-11-26T11:40:00.000Z",
        "priceUSD": 13988.9
      },
      {
        "date": "2024-11-26T15:20:00.000Z",
        "priceUSD": 14097.74
      },
      {
        "date": "2024-11-26T20:44:00.000Z",
        "priceUSD": 14576.34
      },
      {
        "date": "2024-11-27T00:04:00.000Z",
        "priceUSD": 14744.42
      },
      {
        "date": "2024-11-27T03:52:00.000Z",
        "priceUSD": 5828.77
      },
      {
        "date": "2024-11-27T07:16:00.000Z",
        "priceUSD": 6789.2
      },
      {
        "date": "2024-11-27T09:48:00.000Z",
        "priceUSD": 7328.99
      },
      {
        "date": "2024-11-27T14:52:00.000Z",
        "priceUSD": 7865.72
      },
      {
        "date": "2024-11-27T20:02:00.000Z",
        "priceUSD": 8384.59
      },
      {
        "date": "2024-11-28T02:14:00.000Z",
        "priceUSD": 9483.94
      },
      {
        "date": "2024-11-28T07:30:00.000Z",
        "priceUSD": 5611.87
      },
      {
        "date": "2024-11-28T10:20:00.000Z",
        "priceUSD": 6243.91
      },
      {
        "date": "2024-11-28T13:56:00.000Z",
        "priceUSD": 6405.67
      },
      {
        "date": "2024-11-28T17:56:00.000Z",
        "priceUSD": 6649.63
      },
      {
        "date": "2024-11-28T21:04:00.000Z",
        "priceUSD": 7269.02
      },
      {
        "date": "2024-11-29T00:16:00.000Z",
        "priceUSD": 7962.78
      },
      {
        "date": "2024-11-29T05:28:00.000Z",
        "priceUSD": 8515.57
      },
      {
        "date": "2024-11-29T08:34:00.000Z",
        "priceUSD": 9010.26
      },
      {
        "date": "2024-11-29T11:42:00.000Z",
        "priceUSD": 9315.52
      },
      {
        "date": "2024-11-29T14:50:00.000Z",
        "priceUSD": 9395.97
      },
      {
        "date": "2024-11-29T17:58:00.000Z",
        "priceUSD": 4083.95
      },
      {
        "date": "2024-11-29T21:06:00.000Z",
        "priceUSD": 5329.28
      },
      {
        "date": "2024-11-30T00:52:00.000Z",
        "priceUSD": 3479.4
      },
      {
        "date": "2024-11-30T05:12:00.000Z",
        "priceUSD": 4339.02
      },
      {
        "date": "2024-11-30T09:08:00.000Z",
        "priceUSD": 5217.95
      },
      {
        "date": "2024-11-30T16:42:00.000Z",
        "priceUSD": 4512.3
      },
      {
        "date": "2024-11-30T21:32:00.000Z",
        "priceUSD": 5448.65
      },
      {
        "date": "2024-12-01T02:42:00.000Z",
        "priceUSD": 6403.02
      },
      {
        "date": "2024-12-01T05:14:00.000Z",
        "priceUSD": 7005.64
      },
      {
        "date": "2024-12-01T08:22:00.000Z",
        "priceUSD": 7470.7
      },
      {
        "date": "2024-12-01T11:30:00.000Z",
        "priceUSD": 7574.03
      },
      {
        "date": "2024-12-01T14:38:00.000Z",
        "priceUSD": 7491.87
      },
      {
        "date": "2024-12-01T17:46:00.000Z",
        "priceUSD": 7464.68
      },
      {
        "date": "2024-12-01T20:54:00.000Z",
        "priceUSD": 7662.3
      },
      {
        "date": "2024-12-02T00:02:00.000Z",
        "priceUSD": 8384.6
      },
      {
        "date": "2024-12-02T03:32:00.000Z",
        "priceUSD": 8759.95
      },
      {
        "date": "2024-12-02T04:42:00.000Z",
        "priceUSD": 8949.2
      },
      {
        "date": "2024-12-02T10:44:00.000Z",
        "priceUSD": 9924.48
      },
      {
        "date": "2024-12-02T16:56:00.000Z",
        "priceUSD": 10058.49
      },
      {
        "date": "2024-12-03T00:04:00.000Z",
        "priceUSD": 10800.04
      },
      {
        "date": "2024-12-03T03:12:00.000Z",
        "priceUSD": 11349.6
      },
      {
        "date": "2024-12-03T05:02:00.000Z",
        "priceUSD": 11647.58
      },
      {
        "date": "2024-12-03T08:10:00.000Z",
        "priceUSD": 11862.49
      },
      {
        "date": "2024-12-03T11:18:00.000Z",
        "priceUSD": 12306.19
      },
      {
        "date": "2024-12-03T14:26:00.000Z",
        "priceUSD": 12287.64
      },
      {
        "date": "2024-12-03T17:34:00.000Z",
        "priceUSD": 12308.05
      },
      {
        "date": "2024-12-03T20:52:00.000Z",
        "priceUSD": 12751.85
      },
      {
        "date": "2024-12-04T00:58:00.000Z",
        "priceUSD": 5846.67
      },
      {
        "date": "2024-12-04T07:10:00.000Z",
        "priceUSD": 7259.22
      },
      {
        "date": "2024-12-04T12:18:00.000Z",
        "priceUSD": 8267.32
      },
      {
        "date": "2024-12-04T15:26:00.000Z",
        "priceUSD": 8482.28
      },
      {
        "date": "2024-12-04T20:26:00.000Z",
        "priceUSD": 8976.23
      },
      {
        "date": "2024-12-05T02:38:00.000Z",
        "priceUSD": 6037.61
      },
      {
        "date": "2024-12-05T05:16:00.000Z",
        "priceUSD": 6576.32
      },
      {
        "date": "2024-12-05T06:36:00.000Z",
        "priceUSD": 6835.42
      },
      {
        "date": "2024-12-05T09:54:00.000Z",
        "priceUSD": 7594.15
      },
      {
        "date": "2024-12-05T13:02:00.000Z",
        "priceUSD": 7762.86
      },
      {
        "date": "2024-12-05T16:10:00.000Z",
        "priceUSD": 7904.63
      },
      {
        "date": "2024-12-05T17:32:00.000Z",
        "priceUSD": 8077.46
      },
      {
        "date": "2024-12-05T20:56:00.000Z",
        "priceUSD": 8554.28
      },
      {
        "date": "2024-12-06T03:08:00.000Z",
        "priceUSD": 9276.36
      },
      {
        "date": "2024-12-06T10:22:00.000Z",
        "priceUSD": 10079.2
      },
      {
        "date": "2024-12-06T14:32:00.000Z",
        "priceUSD": 10234.66
      },
      {
        "date": "2024-12-06T16:08:00.000Z",
        "priceUSD": 10300.99
      },
      {
        "date": "2024-12-06T17:56:00.000Z",
        "priceUSD": 10447.61
      },
      {
        "date": "2024-12-06T21:44:00.000Z",
        "priceUSD": 10747.6
      },
      {
        "date": "2024-12-07T04:58:00.000Z",
        "priceUSD": 11589.76
      },
      {
        "date": "2024-12-07T07:02:00.000Z",
        "priceUSD": 11763.22
      },
      {
        "date": "2024-12-07T11:10:00.000Z",
        "priceUSD": 12012.91
      },
      {
        "date": "2024-12-07T15:26:00.000Z",
        "priceUSD": 12061.94
      },
      {
        "date": "2024-12-07T18:34:00.000Z",
        "priceUSD": 12126.7
      },
      {
        "date": "2024-12-07T23:36:00.000Z",
        "priceUSD": 12687.46
      },
      {
        "date": "2024-12-08T04:44:00.000Z",
        "priceUSD": 13073.12
      },
      {
        "date": "2024-12-08T10:56:00.000Z",
        "priceUSD": 13564.63
      },
      {
        "date": "2024-12-08T16:06:00.000Z",
        "priceUSD": 13650.89
      },
      {
        "date": "2024-12-08T21:16:00.000Z",
        "priceUSD": 13963.22
      },
      {
        "date": "2024-12-09T04:30:00.000Z",
        "priceUSD": 14720.06
      },
      {
        "date": "2024-12-09T06:36:00.000Z",
        "priceUSD": 14911.8
      },
      {
        "date": "2024-12-09T11:38:00.000Z",
        "priceUSD": 15196.14
      },
      {
        "date": "2024-12-09T15:46:00.000Z",
        "priceUSD": 15207.22
      },
      {
        "date": "2024-12-09T18:08:00.000Z",
        "priceUSD": 15244.71
      },
      {
        "date": "2024-12-09T21:16:00.000Z",
        "priceUSD": 15330.97
      },
      {
        "date": "2024-12-10T00:22:00.000Z",
        "priceUSD": 15749.54
      },
      {
        "date": "2024-12-10T03:30:00.000Z",
        "priceUSD": 15983.44
      },
      {
        "date": "2024-12-10T07:40:00.000Z",
        "priceUSD": 16177.76
      },
      {
        "date": "2024-12-10T10:48:00.000Z",
        "priceUSD": 16303.27
      },
      {
        "date": "2024-12-10T15:32:00.000Z",
        "priceUSD": 16323.64
      },
      {
        "date": "2024-12-10T22:46:00.000Z",
        "priceUSD": 16845.54
      },
      {
        "date": "2024-12-11T02:32:00.000Z",
        "priceUSD": 16994
      },
      {
        "date": "2024-12-11T05:30:00.000Z",
        "priceUSD": 17089.29
      },
      {
        "date": "2024-12-11T09:08:00.000Z",
        "priceUSD": 17265.81
      },
      {
        "date": "2024-12-11T12:54:00.000Z",
        "priceUSD": 17284.43
      },
      {
        "date": "2024-12-11T16:02:00.000Z",
        "priceUSD": 17267
      },
      {
        "date": "2024-12-11T19:10:00.000Z",
        "priceUSD": 17291.71
      },
      {
        "date": "2024-12-11T22:18:00.000Z",
        "priceUSD": 17549.29
      },
      {
        "date": "2024-12-12T00:08:00.000Z",
        "priceUSD": 17639.39
      },
      {
        "date": "2024-12-12T03:16:00.000Z",
        "priceUSD": 17726.56
      },
      {
        "date": "2024-12-12T04:30:00.000Z",
        "priceUSD": 17817.59
      },
      {
        "date": "2024-12-12T07:52:00.000Z",
        "priceUSD": 18024.67
      },
      {
        "date": "2024-12-12T10:24:00.000Z",
        "priceUSD": 18074.24
      },
      {
        "date": "2024-12-12T13:32:00.000Z",
        "priceUSD": 18071.54
      },
      {
        "date": "2024-12-12T16:38:00.000Z",
        "priceUSD": 18044.34
      },
      {
        "date": "2024-12-12T20:16:00.000Z",
        "priceUSD": 18259.69
      },
      {
        "date": "2024-12-13T00:04:00.000Z",
        "priceUSD": 18340.5
      },
      {
        "date": "2024-12-13T04:30:00.000Z",
        "priceUSD": 18428.49
      },
      {
        "date": "2024-12-13T10:42:00.000Z",
        "priceUSD": 18557.31
      },
      {
        "date": "2024-12-13T17:56:00.000Z",
        "priceUSD": 18587.54
      },
      {
        "date": "2024-12-14T02:12:00.000Z",
        "priceUSD": 18932.07
      },
      {
        "date": "2024-12-14T07:22:00.000Z",
        "priceUSD": 19018.34
      },
      {
        "date": "2024-12-14T11:30:00.000Z",
        "priceUSD": 19002.91
      },
      {
        "date": "2024-12-14T14:56:00.000Z",
        "priceUSD": 18964.59
      },
      {
        "date": "2024-12-14T23:16:00.000Z",
        "priceUSD": 19272.29
      },
      {
        "date": "2024-12-15T03:20:00.000Z",
        "priceUSD": 19408.98
      },
      {
        "date": "2024-12-15T10:34:00.000Z",
        "priceUSD": 19509.44
      },
      {
        "date": "2024-12-15T15:14:00.000Z",
        "priceUSD": 19459.57
      },
      {
        "date": "2024-12-15T16:26:00.000Z",
        "priceUSD": 19434.54
      },
      {
        "date": "2024-12-15T19:34:00.000Z",
        "priceUSD": 19436.65
      },
      {
        "date": "2024-12-15T23:32:00.000Z",
        "priceUSD": 5845.67
      },
      {
        "date": "2024-12-16T05:42:00.000Z",
        "priceUSD": 8096.75
      },
      {
        "date": "2024-12-16T09:52:00.000Z",
        "priceUSD": 9309.63
      },
      {
        "date": "2024-12-16T12:36:00.000Z",
        "priceUSD": 9449.12
      },
      {
        "date": "2024-12-16T15:46:00.000Z",
        "priceUSD": 9748.18
      },
      {
        "date": "2024-12-16T18:54:00.000Z",
        "priceUSD": 9956.17
      },
      {
        "date": "2024-12-16T22:02:00.000Z",
        "priceUSD": 10306.58
      },
      {
        "date": "2024-12-17T01:10:00.000Z",
        "priceUSD": 11025.06
      },
      {
        "date": "2024-12-17T03:38:00.000Z",
        "priceUSD": 11604.13
      },
      {
        "date": "2024-12-17T06:22:00.000Z",
        "priceUSD": 11911.51
      },
      {
        "date": "2024-12-17T08:18:00.000Z",
        "priceUSD": 12054.39
      },
      {
        "date": "2024-12-17T11:26:00.000Z",
        "priceUSD": 12268.77
      },
      {
        "date": "2024-12-17T14:34:00.000Z",
        "priceUSD": 12487.05
      },
      {
        "date": "2024-12-17T17:42:00.000Z",
        "priceUSD": 12669.49
      },
      {
        "date": "2024-12-18T00:20:00.000Z",
        "priceUSD": 13349.74
      },
      {
        "date": "2024-12-18T04:20:00.000Z",
        "priceUSD": 13633.76
      },
      {
        "date": "2024-12-18T05:28:00.000Z",
        "priceUSD": 13809.13
      },
      {
        "date": "2024-12-18T10:32:00.000Z",
        "priceUSD": 14158.79
      },
      {
        "date": "2024-12-18T15:28:00.000Z",
        "priceUSD": 14341.19
      },
      {
        "date": "2024-12-18T18:34:00.000Z",
        "priceUSD": 14517.88
      },
      {
        "date": "2024-12-18T21:44:00.000Z",
        "priceUSD": 14781.01
      },
      {
        "date": "2024-12-19T02:52:00.000Z",
        "priceUSD": 15223.42
      },
      {
        "date": "2024-12-19T09:04:00.000Z",
        "priceUSD": 15599.18
      },
      {
        "date": "2024-12-19T14:14:00.000Z",
        "priceUSD": 15882.41
      },
      {
        "date": "2024-12-19T20:26:00.000Z",
        "priceUSD": 16281.31
      },
      {
        "date": "2024-12-20T01:36:00.000Z",
        "priceUSD": 16554.74
      },
      {
        "date": "2024-12-20T07:48:00.000Z",
        "priceUSD": 17208.04
      },
      {
        "date": "2024-12-20T14:44:00.000Z",
        "priceUSD": 17411.79
      },
      {
        "date": "2024-12-20T19:56:00.000Z",
        "priceUSD": 5951.73
      },
      {
        "date": "2024-12-20T23:08:00.000Z",
        "priceUSD": 6535.88
      },
      {
        "date": "2024-12-21T03:06:00.000Z",
        "priceUSD": 7539.13
      },
      {
        "date": "2024-12-21T08:54:00.000Z",
        "priceUSD": 5323.67
      },
      {
        "date": "2024-12-21T13:02:00.000Z",
        "priceUSD": 6207.14
      },
      {
        "date": "2024-12-21T19:48:00.000Z",
        "priceUSD": 6750.37
      },
      {
        "date": "2024-12-22T04:04:00.000Z",
        "priceUSD": 8228.12
      },
      {
        "date": "2024-12-22T13:08:00.000Z",
        "priceUSD": 9138.2
      },
      {
        "date": "2024-12-22T16:28:00.000Z",
        "priceUSD": 9308.1
      },
      {
        "date": "2024-12-23T00:04:00.000Z",
        "priceUSD": 10114.04
      },
      {
        "date": "2024-12-23T03:12:00.000Z",
        "priceUSD": 10311.79
      },
      {
        "date": "2024-12-23T06:18:00.000Z",
        "priceUSD": 10655.19
      },
      {
        "date": "2024-12-23T09:26:00.000Z",
        "priceUSD": 10800.45
      },
      {
        "date": "2024-12-23T14:10:00.000Z",
        "priceUSD": 11032.01
      },
      {
        "date": "2024-12-23T19:20:00.000Z",
        "priceUSD": 11152.96
      },
      {
        "date": "2024-12-23T23:28:00.000Z",
        "priceUSD": 11638.98
      },
      {
        "date": "2024-12-24T01:52:00.000Z",
        "priceUSD": 4573.35
      },
      {
        "date": "2024-12-24T05:40:00.000Z",
        "priceUSD": 5622.35
      },
      {
        "date": "2024-12-24T09:48:00.000Z",
        "priceUSD": 6322.36
      },
      {
        "date": "2024-12-24T15:40:00.000Z",
        "priceUSD": 6960.7
      },
      {
        "date": "2024-12-24T18:48:00.000Z",
        "priceUSD": 7221.77
      },
      {
        "date": "2024-12-24T21:54:00.000Z",
        "priceUSD": 7787.39
      },
      {
        "date": "2024-12-25T01:02:00.000Z",
        "priceUSD": 8063.24
      },
      {
        "date": "2024-12-25T04:24:00.000Z",
        "priceUSD": 8515.06
      },
      {
        "date": "2024-12-25T06:16:00.000Z",
        "priceUSD": 8706.71
      },
      {
        "date": "2024-12-25T09:22:00.000Z",
        "priceUSD": 9054.97
      },
      {
        "date": "2024-12-25T14:10:00.000Z",
        "priceUSD": 9293.62
      },
      {
        "date": "2024-12-25T18:18:00.000Z",
        "priceUSD": 9444.21
      },
      {
        "date": "2024-12-25T22:28:00.000Z",
        "priceUSD": 9932.51
      },
      {
        "date": "2024-12-26T04:24:00.000Z",
        "priceUSD": 10504.62
      },
      {
        "date": "2024-12-26T05:42:00.000Z",
        "priceUSD": 10686.2
      },
      {
        "date": "2024-12-26T09:48:00.000Z",
        "priceUSD": 11024.34
      },
      {
        "date": "2024-12-26T19:06:00.000Z",
        "priceUSD": 11593.25
      },
      {
        "date": "2024-12-26T22:14:00.000Z",
        "priceUSD": 11891.2
      },
      {
        "date": "2024-12-27T02:20:00.000Z",
        "priceUSD": 12297.56
      },
      {
        "date": "2024-12-27T07:30:00.000Z",
        "priceUSD": 12891.42
      },
      {
        "date": "2024-12-27T09:48:00.000Z",
        "priceUSD": 13058.47
      },
      {
        "date": "2024-12-27T12:54:00.000Z",
        "priceUSD": 13290
      },
      {
        "date": "2024-12-27T16:16:00.000Z",
        "priceUSD": 13383.76
      },
      {
        "date": "2024-12-27T19:22:00.000Z",
        "priceUSD": 13617.9
      },
      {
        "date": "2024-12-27T22:30:00.000Z",
        "priceUSD": 13852.78
      },
      {
        "date": "2024-12-28T01:48:00.000Z",
        "priceUSD": 14281.75
      },
      {
        "date": "2024-12-28T06:58:00.000Z",
        "priceUSD": 14765.07
      },
      {
        "date": "2024-12-28T11:56:00.000Z",
        "priceUSD": 15105.05
      },
      {
        "date": "2024-12-28T15:16:00.000Z",
        "priceUSD": 15187.77
      },
      {
        "date": "2024-12-28T19:22:00.000Z",
        "priceUSD": 4303.8
      },
      {
        "date": "2024-12-28T23:50:00.000Z",
        "priceUSD": 5592.77
      },
      {
        "date": "2024-12-29T02:58:00.000Z",
        "priceUSD": 6145.44
      },
      {
        "date": "2024-12-29T04:08:00.000Z",
        "priceUSD": 6855.7
      },
      {
        "date": "2024-12-29T07:48:00.000Z",
        "priceUSD": 7605.95
      },
      {
        "date": "2024-12-29T11:54:00.000Z",
        "priceUSD": 8078.31
      },
      {
        "date": "2024-12-29T19:08:00.000Z",
        "priceUSD": 8686.56
      },
      {
        "date": "2024-12-29T23:38:00.000Z",
        "priceUSD": 9454.73
      },
      {
        "date": "2024-12-30T02:46:00.000Z",
        "priceUSD": 10010.59
      },
      {
        "date": "2024-12-30T05:54:00.000Z",
        "priceUSD": 10249.65
      },
      {
        "date": "2024-12-30T09:12:00.000Z",
        "priceUSD": 10669
      },
      {
        "date": "2024-12-30T13:32:00.000Z",
        "priceUSD": 10897.98
      },
      {
        "date": "2024-12-30T18:36:00.000Z",
        "priceUSD": 11187.01
      },
      {
        "date": "2024-12-30T22:06:00.000Z",
        "priceUSD": 11490.59
      },
      {
        "date": "2024-12-31T01:14:00.000Z",
        "priceUSD": 11879.3
      },
      {
        "date": "2024-12-31T04:22:00.000Z",
        "priceUSD": 12234.97
      },
      {
        "date": "2024-12-31T08:04:00.000Z",
        "priceUSD": 12623.66
      },
      {
        "date": "2024-12-31T13:12:00.000Z",
        "priceUSD": 12817.21
      },
      {
        "date": "2024-12-31T20:26:00.000Z",
        "priceUSD": 13204.63
      },
      {
        "date": "2025-01-01T03:40:00.000Z",
        "priceUSD": 4580.36
      },
      {
        "date": "2025-01-01T08:54:00.000Z",
        "priceUSD": 5379.28
      },
      {
        "date": "2025-01-01T12:02:00.000Z",
        "priceUSD": 5932.53
      },
      {
        "date": "2025-01-01T15:10:00.000Z",
        "priceUSD": 6292.07
      },
      {
        "date": "2025-01-01T19:10:00.000Z",
        "priceUSD": 6821.43
      },
      {
        "date": "2025-01-02T00:20:00.000Z",
        "priceUSD": 7520.71
      },
      {
        "date": "2025-01-02T05:36:00.000Z",
        "priceUSD": 5803.14
      },
      {
        "date": "2025-01-02T08:44:00.000Z",
        "priceUSD": 6480.56
      },
      {
        "date": "2025-01-02T13:16:00.000Z",
        "priceUSD": 6801.15
      },
      {
        "date": "2025-01-02T19:58:00.000Z",
        "priceUSD": 7180.24
      },
      {
        "date": "2025-01-03T01:08:00.000Z",
        "priceUSD": 8115.76
      },
      {
        "date": "2025-01-03T06:16:00.000Z",
        "priceUSD": 8586.14
      },
      {
        "date": "2025-01-03T09:24:00.000Z",
        "priceUSD": 8980.45
      },
      {
        "date": "2025-01-03T14:40:00.000Z",
        "priceUSD": 9213.43
      },
      {
        "date": "2025-01-03T20:48:00.000Z",
        "priceUSD": 9817.82
      },
      {
        "date": "2025-01-04T04:04:00.000Z",
        "priceUSD": 10444.87
      },
      {
        "date": "2025-01-04T09:12:00.000Z",
        "priceUSD": 11063.6
      },
      {
        "date": "2025-01-04T16:20:00.000Z",
        "priceUSD": 11329.81
      },
      {
        "date": "2025-01-04T19:26:00.000Z",
        "priceUSD": 11428.1
      },
      {
        "date": "2025-01-04T22:34:00.000Z",
        "priceUSD": 11901.85
      },
      {
        "date": "2025-01-05T01:42:00.000Z",
        "priceUSD": 4365.89
      },
      {
        "date": "2025-01-05T04:50:00.000Z",
        "priceUSD": 5605.78
      },
      {
        "date": "2025-01-05T08:08:00.000Z",
        "priceUSD": 6468.61
      },
      {
        "date": "2025-01-05T16:24:00.000Z",
        "priceUSD": 7258.24
      },
      {
        "date": "2025-01-05T20:32:00.000Z",
        "priceUSD": 7809.45
      },
      {
        "date": "2025-01-06T02:44:00.000Z",
        "priceUSD": 8760.46
      },
      {
        "date": "2025-01-06T09:58:00.000Z",
        "priceUSD": 9718.35
      },
      {
        "date": "2025-01-06T13:06:00.000Z",
        "priceUSD": 9804.43
      },
      {
        "date": "2025-01-06T16:14:00.000Z",
        "priceUSD": 9918.86
      },
      {
        "date": "2025-01-06T19:22:00.000Z",
        "priceUSD": 4132.07
      },
      {
        "date": "2025-01-06T22:30:00.000Z",
        "priceUSD": 4747.4
      },
      {
        "date": "2025-01-07T00:44:00.000Z",
        "priceUSD": 5042.08
      },
      {
        "date": "2025-01-07T04:28:00.000Z",
        "priceUSD": 6115.56
      },
      {
        "date": "2025-01-07T10:38:00.000Z",
        "priceUSD": 7398.75
      },
      {
        "date": "2025-01-07T14:04:00.000Z",
        "priceUSD": 7497.2
      },
      {
        "date": "2025-01-07T19:44:00.000Z",
        "priceUSD": 7873.59
      },
      {
        "date": "2025-01-07T21:32:00.000Z",
        "priceUSD": 8174.58
      },
      {
        "date": "2025-01-07T23:24:00.000Z",
        "priceUSD": 8430.1
      },
      {
        "date": "2025-01-08T02:32:00.000Z",
        "priceUSD": 8808.82
      },
      {
        "date": "2025-01-08T05:20:00.000Z",
        "priceUSD": 9127.29
      },
      {
        "date": "2025-01-08T08:24:00.000Z",
        "priceUSD": 9307.34
      },
      {
        "date": "2025-01-08T12:44:00.000Z",
        "priceUSD": 4768.04
      },
      {
        "date": "2025-01-08T16:54:00.000Z",
        "priceUSD": 5116.41
      },
      {
        "date": "2025-01-08T20:02:00.000Z",
        "priceUSD": 5438.06
      },
      {
        "date": "2025-01-08T23:10:00.000Z",
        "priceUSD": 6255.2
      },
      {
        "date": "2025-01-09T03:08:00.000Z",
        "priceUSD": 6838.63
      },
      {
        "date": "2025-01-09T09:20:00.000Z",
        "priceUSD": 7791.52
      },
      {
        "date": "2025-01-09T11:00:00.000Z",
        "priceUSD": 7947.96
      },
      {
        "date": "2025-01-09T14:24:00.000Z",
        "priceUSD": 8121.41
      },
      {
        "date": "2025-01-09T18:32:00.000Z",
        "priceUSD": 8317.87
      },
      {
        "date": "2025-01-10T00:42:00.000Z",
        "priceUSD": 9035.43
      },
      {
        "date": "2025-01-10T05:52:00.000Z",
        "priceUSD": 9655.72
      },
      {
        "date": "2025-01-10T13:06:00.000Z",
        "priceUSD": 9917.24
      },
      {
        "date": "2025-01-10T19:04:00.000Z",
        "priceUSD": 10298.69
      },
      {
        "date": "2025-01-11T02:18:00.000Z",
        "priceUSD": 10772.54
      },
      {
        "date": "2025-01-11T04:12:00.000Z",
        "priceUSD": 10944.71
      },
      {
        "date": "2025-01-11T07:16:00.000Z",
        "priceUSD": 11246.51
      },
      {
        "date": "2025-01-11T11:08:00.000Z",
        "priceUSD": 11430.39
      },
      {
        "date": "2025-01-11T17:20:00.000Z",
        "priceUSD": 11585.24
      },
      {
        "date": "2025-01-11T19:16:00.000Z",
        "priceUSD": 11672.79
      },
      {
        "date": "2025-01-11T22:24:00.000Z",
        "priceUSD": 12078.86
      },
      {
        "date": "2025-01-12T01:36:00.000Z",
        "priceUSD": 12269.65
      },
      {
        "date": "2025-01-12T07:48:00.000Z",
        "priceUSD": 12903.47
      },
      {
        "date": "2025-01-12T10:48:00.000Z",
        "priceUSD": 12994.7
      },
      {
        "date": "2025-01-12T13:54:00.000Z",
        "priceUSD": 13128.11
      },
      {
        "date": "2025-01-12T17:02:00.000Z",
        "priceUSD": 13173.79
      },
      {
        "date": "2025-01-12T20:10:00.000Z",
        "priceUSD": 13450.14
      },
      {
        "date": "2025-01-12T23:20:00.000Z",
        "priceUSD": 13663
      },
      {
        "date": "2025-01-13T03:26:00.000Z",
        "priceUSD": 13973.71
      },
      {
        "date": "2025-01-13T08:36:00.000Z",
        "priceUSD": 14239.03
      },
      {
        "date": "2025-01-13T16:24:00.000Z",
        "priceUSD": 14445.49
      },
      {
        "date": "2025-01-13T19:32:00.000Z",
        "priceUSD": 14599.08
      },
      {
        "date": "2025-01-13T23:38:00.000Z",
        "priceUSD": 14846.25
      },
      {
        "date": "2025-01-14T02:20:00.000Z",
        "priceUSD": 14962.8
      },
      {
        "date": "2025-01-14T05:26:00.000Z",
        "priceUSD": 15185.97
      },
      {
        "date": "2025-01-14T08:34:00.000Z",
        "priceUSD": 15377.98
      },
      {
        "date": "2025-01-14T11:42:00.000Z",
        "priceUSD": 15445.62
      },
      {
        "date": "2025-01-14T14:12:00.000Z",
        "priceUSD": 15472.86
      },
      {
        "date": "2025-01-14T18:14:00.000Z",
        "priceUSD": 15516.28
      },
      {
        "date": "2025-01-15T00:26:00.000Z",
        "priceUSD": 15879.03
      },
      {
        "date": "2025-01-15T05:36:00.000Z",
        "priceUSD": 16031.37
      },
      {
        "date": "2025-01-15T10:40:00.000Z",
        "priceUSD": 16215.18
      },
      {
        "date": "2025-01-15T12:08:00.000Z",
        "priceUSD": 16230.55
      },
      {
        "date": "2025-01-15T15:14:00.000Z",
        "priceUSD": 16243.55
      },
      {
        "date": "2025-01-15T18:22:00.000Z",
        "priceUSD": 16310.28
      },
      {
        "date": "2025-01-15T21:30:00.000Z",
        "priceUSD": 16418.75
      },
      {
        "date": "2025-01-15T23:20:00.000Z",
        "priceUSD": 16497.97
      },
      {
        "date": "2025-01-16T00:28:00.000Z",
        "priceUSD": 16575.75
      },
      {
        "date": "2025-01-16T04:04:00.000Z",
        "priceUSD": 16734.19
      },
      {
        "date": "2025-01-16T10:10:00.000Z",
        "priceUSD": 16943.88
      },
      {
        "date": "2025-01-16T13:18:00.000Z",
        "priceUSD": 16940.9
      },
      {
        "date": "2025-01-16T16:26:00.000Z",
        "priceUSD": 16938.44
      },
      {
        "date": "2025-01-16T19:26:00.000Z",
        "priceUSD": 16991.47
      },
      {
        "date": "2025-01-16T22:34:00.000Z",
        "priceUSD": 17049.32
      },
      {
        "date": "2025-01-17T02:20:00.000Z",
        "priceUSD": 17182.58
      },
      {
        "date": "2025-01-17T07:16:00.000Z",
        "priceUSD": 17380.08
      },
      {
        "date": "2025-01-17T10:22:00.000Z",
        "priceUSD": 17421.42
      },
      {
        "date": "2025-01-17T12:24:00.000Z",
        "priceUSD": 17433.94
      },
      {
        "date": "2025-01-17T15:44:00.000Z",
        "priceUSD": 17438.51
      },
      {
        "date": "2025-01-17T18:20:00.000Z",
        "priceUSD": 17471.45
      },
      {
        "date": "2025-01-17T23:24:00.000Z",
        "priceUSD": 17711.79
      },
      {
        "date": "2025-01-18T04:34:00.000Z",
        "priceUSD": 17789.66
      },
      {
        "date": "2025-01-18T09:44:00.000Z",
        "priceUSD": 17931.12
      },
      {
        "date": "2025-01-18T15:34:00.000Z",
        "priceUSD": 17966.06
      },
      {
        "date": "2025-01-18T18:42:00.000Z",
        "priceUSD": 17975.34
      },
      {
        "date": "2025-01-18T21:50:00.000Z",
        "priceUSD": 18129.23
      },
      {
        "date": "2025-01-19T00:58:00.000Z",
        "priceUSD": 18235.84
      },
      {
        "date": "2025-01-19T04:06:00.000Z",
        "priceUSD": 18293.38
      },
      {
        "date": "2025-01-19T07:14:00.000Z",
        "priceUSD": 18392.25
      },
      {
        "date": "2025-01-19T10:32:00.000Z",
        "priceUSD": 18448.22
      },
      {
        "date": "2025-01-19T15:20:00.000Z",
        "priceUSD": 18464.65
      },
      {
        "date": "2025-01-19T18:48:00.000Z",
        "priceUSD": 18513.67
      },
      {
        "date": "2025-01-20T01:00:00.000Z",
        "priceUSD": 18762.7
      },
      {
        "date": "2025-01-20T04:42:00.000Z",
        "priceUSD": 18880.56
      },
      {
        "date": "2025-01-20T07:50:00.000Z",
        "priceUSD": 18968.09
      },
      {
        "date": "2025-01-20T11:00:00.000Z",
        "priceUSD": 18974.54
      },
      {
        "date": "2025-01-20T14:06:00.000Z",
        "priceUSD": 18987.7
      },
      {
        "date": "2025-01-20T17:14:00.000Z",
        "priceUSD": 18990.48
      },
      {
        "date": "2025-01-20T20:22:00.000Z",
        "priceUSD": 19156.46
      },
      {
        "date": "2025-01-20T22:52:00.000Z",
        "priceUSD": 19209.41
      },
      {
        "date": "2025-01-21T04:10:00.000Z",
        "priceUSD": 19380.11
      },
      {
        "date": "2025-01-21T09:52:00.000Z",
        "priceUSD": 19481.65
      },
      {
        "date": "2025-01-21T11:46:00.000Z",
        "priceUSD": 19490.86
      },
      {
        "date": "2025-01-21T23:12:00.000Z",
        "priceUSD": 19652.78
      },
      {
        "date": "2025-01-22T02:20:00.000Z",
        "priceUSD": 19749.93
      },
      {
        "date": "2025-01-22T05:26:00.000Z",
        "priceUSD": 19853.48
      },
      {
        "date": "2025-01-22T08:34:00.000Z",
        "priceUSD": 19901.4
      },
      {
        "date": "2025-01-22T11:42:00.000Z",
        "priceUSD": 19943.43
      },
      {
        "date": "2025-01-22T14:52:00.000Z",
        "priceUSD": 19944.93
      },
      {
        "date": "2025-01-22T17:58:00.000Z",
        "priceUSD": 19965.48
      },
      {
        "date": "2025-01-22T21:06:00.000Z",
        "priceUSD": 20099.83
      },
      {
        "date": "2025-01-23T00:36:00.000Z",
        "priceUSD": 20142.97
      },
      {
        "date": "2025-01-23T04:42:00.000Z",
        "priceUSD": 20281.44
      },
      {
        "date": "2025-01-23T10:54:00.000Z",
        "priceUSD": 20396.96
      },
      {
        "date": "2025-01-23T16:32:00.000Z",
        "priceUSD": 20440.34
      },
      {
        "date": "2025-01-24T00:48:00.000Z",
        "priceUSD": 20665.5
      },
      {
        "date": "2025-01-24T05:34:00.000Z",
        "priceUSD": 20752.72
      },
      {
        "date": "2025-01-24T08:42:00.000Z",
        "priceUSD": 20825.05
      },
      {
        "date": "2025-01-24T13:06:00.000Z",
        "priceUSD": 20867.17
      },
      {
        "date": "2025-01-24T16:14:00.000Z",
        "priceUSD": 20900.43
      },
      {
        "date": "2025-01-24T19:22:00.000Z",
        "priceUSD": 20930.38
      },
      {
        "date": "2025-01-24T22:30:00.000Z",
        "priceUSD": 21103.2
      },
      {
        "date": "2025-01-25T01:38:00.000Z",
        "priceUSD": 21151.09
      },
      {
        "date": "2025-01-25T06:28:00.000Z",
        "priceUSD": 21291.47
      },
      {
        "date": "2025-01-25T09:40:00.000Z",
        "priceUSD": 21328.79
      },
      {
        "date": "2025-01-25T12:32:00.000Z",
        "priceUSD": 21347.16
      },
      {
        "date": "2025-01-25T15:52:00.000Z",
        "priceUSD": 21355.03
      },
      {
        "date": "2025-01-25T23:10:00.000Z",
        "priceUSD": 21608.65
      },
      {
        "date": "2025-01-26T04:16:00.000Z",
        "priceUSD": 21785.02
      }
    ],
    "listPriceHistory": null,
    "collectiblePriceHistory": null,
    "refurbishedPriceHistory": null
  },
  "title": "Dragon Ball Z figurine S.H.Figuarts King Cold 22 cm",
  "frequentlyBoughtTogether": [
    "B09BCKFQW8",
    "B09TFB192X"
  ],
  "listedSince": 7223592,
  "itemHeight": 13,
  "itemLength": 100,
  "itemWeight": 500,
  "itemWidth": 50
}